Workbook

Sheet Honor Pledge
A1: On my honor, I, Josh Cha,have neither given nor received unauthorized aid in doing this assignment.

Sheet Class Budget Data
A1: Home (Rent rent insurance etc) | B1: Cell phone | C1: Cable or Internet | D1: Car - Monthly payment | E1: Car - Gasoline | F1: Other Transportation (bus etc) | G1: Groceries (e.g. Walmart) | H1: Restaurants / fast food/ coffee shops | I1: Daycare/kids | J1: Clothing | K1: School supplies | L1: Fun stuff (parties movies hobbies etc) | M1: Savings for unexpected expenses | N1: Savings for Retirement (e.g savings to ROTH IRA account) | O1: Subscriptions (Apple music Amazon music Netflix Disney + etc) | P1: Travel | Q1: Payments to loans | R1: What is your monthly income? - /month
A2: 900 | B2: 30 | C2: 50 | D2: 400 | E2: 50 | F2: 25 | G2: 120 | H2: 300 | I2: 500 | J2: 50 | K2: 20 | L2: 50 | M2: 1000 | N2: 500 | O2: 45 | P2: 200 | Q2: 500 | R2: 3000
A3: 583 | B3: 50 | C3: 40 | D3: 375 | E3: 125 | F3: 50 | G3: 200 | H3: 50 | J3: 75 | K3: 20 | L3: 200 | M3: 100 | N3: 100 | O3: 20 | P3: 40 | Q3: 200 | R3: 700
A4: 1100 | B4: 30 | C4: 50 | D4: 400 | E4: 131.76 | F4: 40 | G4: 70 | H4: 200 | J4: 50 | K4: 30 | L4: 80 | M4: 100 | N4: 100 | O4: 10 | P4: 300 | Q4: 50 | R4: 700
A5: 900 | B5: 40 | C5: 50 | D5: 750 | E5: 100 | F5: 50 | G5: 240 | H5: 250 | J5: 70 | K5: 50 | L5: 50 | M5: 150 | N5: 500 | O5: 100 | P5: 100 | Q5: 200 | R5: 60
A6: 1200 | B6: 40 | C6: 20 | D6: 2000 | E6: 100 | F6: 50 | G6: 200 | H6: 200 | J6: 10 | K6: 40 | L6: 30 | M6: 300 | N6: 300 | O6: 40 | P6: 25 | Q6: 200 | R6: 50
A7: 1200 | B7: 75 | C7: 10 | D7: 100 | E7: 10 | F7: 1200 | G7: 200 | H7: 250 | J7: 50 | K7: 15 | L7: 50 | M7: 200 | N7: 100 | O7: 15 | P7: 200 | Q7: 50 | R7: 4000
A8: 583 | B8: 150 | C8: 100 | D8: 700 | E8: 60 | F8: 60 | G8: 600 | H8: 250 | J8: 50 | K8: 20 | L8: 25 | M8: 100 | N8: 200 | O8: 6 | P8: 10 | Q8: 200 | R8: 2700
A9: 1600 | B9: 120 | C9: 20 | D9: 170 | E9: 40 | F9: 10 | G9: 150 | H9: 600 | J9: 20 | K9: 10 | L9: 50 | M9: 100 | N9: 10 | O9: 138 | P9: 100 | Q9: 60 | R9: 1600
A10: 1000 | B10: 40 | C10: 75 | D10: 2000 | E10: 45 | F10: 100 | G10: 300 | H10: 300 | J10: 200 | K10: 10 | L10: 20 | M10: 500 | N10: 100 | O10: 5 | P10: 100 | Q10: 50 | R10: 1000
A11: 900 | B11: 85 | C11: 10 | D11: 200 | E11: 10 | F11: 30 | G11: 400 | H11: 50 | J11: 50 | K11: 120 | L11: 50 | M11: 100 | N11: 100 | O11: 7 | P11: 150 | Q11: 63 | R11: 1000
A12: 2000 | B12: 120 | C12: 30 | D12: 250 | E12: 60 | F12: 5 | G12: 300 | H12: 100 | J12: 100 | K12: 10 | L12: 50 | M12: 10 | N12: 400 | O12: 15 | P12: 1000 | Q12: 1500 | R12: 1000
A13: 1100 | B13: 65 | C13: 12.5 | D13: 2000 | E13: 120 | F13: 50 | G13: 50 | H13: 250 | J13: 50 | K13: 10 | L13: 50 | M13: 100 | N13: 100 | O13: 50 | P13: 50 | Q13: 500 | R13: 80000
A14: 850 | B14: 50 | C14: 80 | D14: 400 | E14: 180 | F14: 50 | G14: 50 | H14: 100 | J14: 50 | K14: 20 | L14: 250 | M14: 400 | N14: 80 | O14: 150 | P14: 100 | R14: 80000
A15: 850 | B15: 25 | C15: 50 | D15: 60 | E15: 40 | F15: 20 | G15: 400 | H15: 75 | J15: 25 | K15: 100 | L15: 80 | M15: 20 | N15: 100 | O15: 50 | P15: 300 | R15: 70000
A16: 1300 | B16: 100 | C16: 10 | D16: 500 | E16: 100 | F16: 15 | G16: 90 | H16: 50 | J16: 30 | K16: 6.25 | L16: 50 | M16: 350 | N16: 100 | O16: 6.6 | P16: 15 | R16: 48000
A17: 537 | B17: 30 | C17: 40 | D17: 250 | E17: 100 | F17: 35 | G17: 50 | H17: 20 | J17: 150 | K17: 2 | L17: 1000 | M17: 15 | N17: 200 | O17: 10 | P17: 100 | R17: 35000
A18: 970 | B18: 50 | C18: 150 | D18: 100 | E18: 100 | F18: 80 | G18: 85 | H18: 400 | J18: 30 | K18: 10 | L18: 50 | M18: 40 | N18: 100 | O18: 150 | P18: 230 | R18: 25000
A19: 600 | B19: 55 | C19: 30 | D19: 615 | E19: 75 | F19: 100 | G19: 20 | H19: 120 | J19: 100 | K19: 40 | L19: 300 | M19: 100 | N19: 100 | O19: 150 | P19: 100 | R19: 15000
A20: 650 | B20: 30 | C20: 50 | D20: 357 | E20: 40 | F20: 100 | G20: 100 | H20: 300 | J20: 150 | K20: 30 | L20: 60 | M20: 400 | N20: 10 | O20: 15 | P20: 25 | R20: 10000
A21: 1000 | B21: 25 | C21: 100 | D21: 400 | E21: 40 | F21: 16 | G21: 100 | H21: 40 | J21: 50 | K21: 50 | L21: 400 | M21: 5 | N21: 80 | O21: 20 | P21: 40 | R21: 10000
A22: 700 | B22: 25 | C22: 20 | D22: 200 | E22: 60 | F22: 33 | G22: 250 | H22: 50 | J22: 100 | K22: 20 | L22: 150 | M22: 100 | N22: 200 | O22: 50 | P22: 42 | R22: 10000
A23: 800 | B23: 200 | C23: 50 | D23: 300 | E23: 30 | F23: 20 | G23: 200 | H23: 50 | J23: 70 | K23: 37.5 | L23: 500 | M23: 100 | N23: 200 | O23: 20 | P23: 300 | R23: 9000
A24: 1100 | B24: 80 | C24: 40 | D24: 500 | E24: 58 | F24: 100 | G24: 400 | H24: 1000 | J24: 50 | K24: 10 | L24: 35 | M24: 200 | N24: 500 | O24: 10 | P24: 30 | R24: 9000
A25: 1100 | B25: 40 | C25: 70 | D25: 200 | E25: 35 | F25: 100 | G25: 240 | H25: 150 | J25: 15 | K25: 15 | L25: 100 | M25: 500 | N25: 200 | O25: 20 | P25: 200 | R25: 7000
... A111: 850 | B111: 100 | C111: 30 | D111: 145 | E111: 45 | F111: 100 | G111: 200 | H111: 300 | J111: 50 | K111: 20 | L111: 50 | M111: 100 | N111: 1000 | O111: 100 | P111: 400 | R111: 1400
A112: 300 | B112: 100 | C112: 35 | E112: 80 | G112: 100 | H112: 500 | J112: 200 | K112: 20 | L112: 50 | M112: 10 | N112: 50 | O112: 20 | P112: 600 | R112: 1300
A113: 1100 | B113: 10 | C113: 30 | E113: 75 | G113: 180 | H113: 60 | J113: 50 | K113: 25 | L113: 45 | M113: 2000 | N113: 100 | O113: 20 | P113: 900 | R113: 1300
A114: 1000 | B114: 200 | C114: 20 | E114: 150 | G114: 100 | H114: 170 | J114: 50 | K114: 30 | L114: 20 | M114: 40 | N114: 10 | O114: 25 | P114: 120 | R114: 1300
A115: 725 | B115: 50 | C115: 25 | E115: 90 | G115: 250 | H115: 30 | J115: 20 | K115: 10 | L115: 40 | M115: 50 | N115: 200 | O115: 25 | P115: 100 | R115: 1300
A116: 711 | B116: 50 | C116: 20 | E116: 120 | G116: 256 | H116: 600 | J116: 30 | K116: 20 | L116: 200 | M116: 50 | N116: 200 | O116: 30 | P116: 100 | R116: 1300
A117: 800 | B117: 80 | C117: 35 | E117: 60 | G117: 130 | H117: 100 | J117: 50 | K117: 30 | L117: 50 | M117: 291 | N117: 500 | O117: 15 | P117: 100 | R117: 1300
A118: 1080 | B118: 20 | C118: 100 | E118: 120 | G118: 150 | H118: 100 | J118: 20 | K118: 50 | L118: 10 | M118: 160 | N118: 50 | O118: 500 | P118: 100 | R118: 1300
A119: 1000 | B119: 50 | C119: 50 | E119: 30 | G119: 300 | H119: 25 | J119: 200 | K119: 10 | L119: 50 | M119: 100 | N119: 300 | O119: 100 | P119: 80 | R119: 1200
A120: 1400 | B120: 8 | C120: 50 | E120: 75 | G120: 1200 | H120: 50 | J120: 50 | K120: 20 | L120: 200 | M120: 80 | N120: 100 | O120: 60 | P120: 50 | R120: 1200
A121: 900 | B121: 45 | C121: 50 | E121: 80 | G121: 100 | H121: 30 | J121: 5 | K121: 10 | L121: 50 | M121: 50 | N121: 25 | O121: 55 | P121: 50 | R121: 1200
A122: 1000 | B122: 19 | C122: 50 | E122: 80 | G122: 100 | H122: 200 | J122: 300 | K122: 10 | L122: 200 | M122: 100 | N122: 50 | O122: 30 | P122: 25 | R122: 1200
A123: 70 | B123: 62 | C123: 10 | E123: 150 | G123: 300 | H123: 3000 | J123: 20 | K123: 50 | L123: 50 | M123: 1000 | N123: 200 | O123: 10 | P123: 100 | R123: 1200
A124: 750 | B124: 50 | C124: 50 | E124: 100 | G124: 300 | H124: 200 | J124: 200 | K124: 10 | L124: 50 | M124: 50 | N124: 45 | O124: 20 | P124: 1200 | R124: 1100
A125: 725 | B125: 100 | C125: 30 | E125: 150 | G125: 200 | H125: 200 | J125: 30 | K125: 20 | L125: 30 | M125: 500 | O125: 20 | P125: 200 | R125: 1100
A126: 1000 | B126: 70 | C126: 15 | E126: 50 | G126: 200 | H126: 500 | J126: 100 | K126: 50 | L126: 100 | M126: 200 | O126: 20 | P126: 100 | R126: 1087
A127: 560 | B127: 15 | C127: 50 | E127: 80 | G127: 200 | H127: 50 | J127: 300 | K127: 10 | L127: 250 | M127: 100 | O127: 30 | P127: 50 | R127: 1063
A128: 830 | B128: 40 | C128: 89.99 | E128: 100 | G128: 50 | H128: 10 | J128: 10 | K128: 20 | L128: 100 | M128: 200 | O128: 100 | P128: 50 | R128: 1024
A129: 665 | B129: 100 | C129: 80 | E129: 200 | G129: 300 | H129: 250 | J129: 100 | K129: 50 | L129: 50 | M129: 1000 | O129: 10 | P129: 100 | R129: 1000
A130: 592 | B130: 30 | C130: 20 | E130: 80 | G130: 300 | H130: 150 | J130: 75 | K130: 10 | L130: 100 | M130: 150 | O130: 400 | P130: 65 | R130: 1000
A131: 850 | B131: 39 | C131: 40 | E131: 100 | G131: 400 | H131: 100 | J131: 500 | K131: 10 | L131: 100 | M131: 30 | O131: 250 | P131: 60 | R131: 1000
A132: 900 | B132: 50 | C132: 50 | E132: 200 | G132: 180 | H132: 40 | J132: 30 | K132: 5 | L132: 50 | M132: 120 | O132: 150 | P132: 500 | R132: 1000
A133: 900 | B133: 80 | C133: 35 | E133: 50 | G133: 300 | H133: 250 | J133: 50 | K133: 10 | L133: 30 | M133: 50 | O133: 100 | P133: 500 | R133: 1000
A134: 1300 | B134: 40 | C134: 25 | E134: 500 | G134: 300 | H134: 120 | J134: 30 | K134: 20 | L134: 200 | M134: 17 | O134: 30 | P134: 50 | R134: 1000
A135: 200 | B135: 141 | C135: 45 | E135: 100 | G135: 200 | H135: 300 | J135: 10 | K135: 60 | L135: 100 | M135: 15 | O135: 30 | P135: 500 | R135: 1000
A136: 2049 | B136: 30 | C136: 10 | E136: 150 | G136: 280 | H136: 75 | J136: 50 | K136: 100 | L136: 50 | M136: 100 | O136: 1000 | P136: 70 | R136: 1000
... A160: 850 | B160: 200 | C160: 51 | E160: 60 | G160: 100 | H160: 100 | J160: 5 | K160: 20 | L160: 50 | M160: 20 | O160: 30 | P160: 80 | R160: 800
A161: 1400 | B161: 25 | E161: 50 | G161: 400 | H161: 80 | J161: 50 | K161: 10 | L161: 100 | M161: 100 | O161: 12 | P161: 50 | R161: 800
A162: 1000 | B162: 50 | E162: 60 | G162: 120 | H162: 40 | J162: 30 | K162: 20 | L162: 50 | M162: 100 | O162: 12 | P162: 150 | R162: 800
A163: 860 | B163: 20 | E163: 80 | G163: 60 | H163: 300 | J163: 20 | K163: 5 | L163: 150 | M163: 200 | O163: 10 | P163: 50 | R163: 800
A164: 750 | B164: 55 | E164: 70 | G164: 150 | H164: 50 | J164: 100 | K164: 100 | L164: 50 | M164: 50 | O164: 10 | P164: 50 | R164: 800
A165: 2000 | B165: 70 | E165: 100 | G165: 200 | H165: 100 | J165: 100 | K165: 10 | L165: 100 | M165: 40 | O165: 15 | P165: 65 | R165: 750
A166: 500 | B166: 70 | E166: 100 | G166: 200 | H166: 100 | J166: 50 | K166: 20 | L166: 120 | M166: 100 | O166: 20 | P166: 40 | R166: 750
A167: 1000 | B167: 75 | E167: 100 | G167: 300 | H167: 200 | J167: 20 | K167: 30 | L167: 300 | M167: 50 | O167: 20 | P167: 50 | R167: 750
A168: 1000 | B168: 60 | E168: 120 | G168: 300 | H168: 150 | J168: 100 | K168: 15 | L168: 50 | M168: 100 | O168: 8 | P168: 500 | R168: 720
A169: 700 | B169: 77 | E169: 80 | G169: 400 | H169: 50 | J169: 50 | K169: 20 | L169: 100 | M169: 200 | O169: 8 | P169: 100 | R169: 700
A170: 1250 | B170: 50 | E170: 32.5 | G170: 150 | H170: 150 | J170: 50 | K170: 50 | L170: 200 | M170: 450 | O170: 8 | P170: 100 | R170: 700
A171: 850 | B171: 40 | E171: 40 | G171: 100 | H171: 70 | J171: 20 | K171: 25 | L171: 20 | M171: 100 | O171: 24 | P171: 20 | R171: 650
A172: 1100 | B172: 25 | E172: 100 | G172: 300 | H172: 100 | J172: 50 | K172: 10 | L172: 100 | M172: 100 | O172: 20 | P172: 85 | R172: 600
... A188: 1500 | B188: 20 | E188: 100 | G188: 100 | H188: 200 | J188: 75 | K188: 25 | L188: 15 | M188: 300 | O188: 50 | P188: 20 | R188: 500
A189: 860 | B189: 61 | E189: 200 | G189: 200 | H189: 200 | J189: 50 | K189: 20 | L189: 100 | M189: 80 | O189: 15 | R189: 500
A190: 500 | B190: 70 | E190: 80 | G190: 300 | H190: 60 | J190: 50 | K190: 30 | L190: 200 | M190: 250 | O190: 20 | R190: 500
A191: 941.5 | B191: 120 | E191: 70 | G191: 100 | H191: 50 | J191: 150 | K191: 20 | L191: 50 | M191: 20 | O191: 15 | R191: 500
A192: 650 | B192: 100 | E192: 100 | G192: 50 | H192: 30 | J192: 100 | K192: 30 | L192: 50 | M192: 1000 | O192: 20 | R192: 500
A193: 1200 | B193: 120 | E193: 80 | G193: 200 | H193: 50 | J193: 25 | K193: 50 | L193: 100 | M193: 100 | O193: 20 | R193: 500
A194: 600 | B194: 60 | E194: 80 | G194: 100 | H194: 100 | J194: 50 | K194: 5 | L194: 200 | M194: 250 | O194: 15 | R194: 500
A195: 1500 | B195: 50 | E195: 60 | G195: 20 | H195: 100 | J195: 20 | K195: 15 | L195: 400 | M195: 75 | O195: 100 | R195: 500
A196: 1000 | B196: 50 | E196: 300 | G196: 75 | H196: 100 | J196: 20 | K196: 40 | L196: 300 | M196: 50 | O196: 100 | R196: 500
A197: 1300 | B197: 50 | E197: 60 | G197: 100 | H197: 50 | J197: 50 | K197: 5 | L197: 150 | M197: 200 | O197: 30 | R197: 500
A198: 1000 | B198: 35 | E198: 50 | G198: 480 | H198: 80 | J198: 25 | K198: 25 | L198: 50 | M198: 100 | O198: 6 | R198: 460
A199: 950 | B199: 20 | E199: 90 | G199: 50 | H199: 50 | J199: 200 | K199: 50 | L199: 100 | M199: 30 | O199: 25 | R199: 450
A200: 600 | B200: 50 | E200: 350 | G200: 50 | H200: 70 | J200: 25 | K200: 150 | L200: 200 | M200: 1000 | O200: 50 | R200: 450
... A236: 850 | B236: 20 | E236: 150 | G236: 65 | H236: 300 | J236: 100 | K236: 20 | L236: 50 | M236: 100 | O236: 60 | R236: 35
A237: 1100 | B237: 40 | E237: 150 | G237: 200 | H237: 100 | J237: 10 | K237: 20 | L237: 150 | M237: 150 | O237: 75
A238: 627.2 | E238: 80 | G238: 80 | H238: 100 | J238: 100 | K238: 10 | L238: 35 | M238: 100 | O238: 50
A239: 1400 | E239: 60 | G239: 200 | H239: 100 | J239: 60 | K239: 50 | L239: 500 | M239: 80 | O239: 40
A240: 1200 | E240: 75 | G240: 300 | H240: 300 | J240: 50 | K240: 20 | L240: 20 | M240: 50 | O240: 50
A241: 1000 | E241: 60 | G241: 400 | H241: 180 | J241: 75 | K241: 15 | L241: 50 | M241: 2000 | O241: 10
A242: 1000 | E242: 200 | G242: 150 | H242: 25 | J242: 40 | K242: 30 | L242: 150 | O242: 100
A243: 3000 | E243: 80 | G243: 90 | H243: 60 | J243: 50 | K243: 20 | L243: 200 | O243: 20
A244: 1200 | E244: 200 | G244: 125 | H244: 450 | J244: 100 | K244: 60 | L244: 100 | O244: 20
A245: 400 | E245: 50 | G245: 350 | H245: 200 | J245: 50 | K245: 10 | L245: 30 | O245: 100
A246: 900 | E246: 40 | G246: 280 | H246: 25 | J246: 150 | K246: 25 | L246: 350 | O246: 15
A247: 2450 | E247: 60 | G247: 400 | H247: 200 | J247: 200 | K247: 100 | L247: 100 | O247: 25
A248: 1200 | E248: 100 | G248: 30 | H248: 100 | J248: 50 | K248: 100 | L248: 120 | O248: 40
A249: 1100 | E249: 50 | G249: 30 | H249: 500 | J249: 100 | K249: 10 | L249: 500 | O249: 50
A250: 1800 | E250: 135 | G250: 500 | H250: 25 | J250: 125 | K250: 100 | L250: 150 | O250: 20
A251: 1230 | E251: 100 | G251: 250 | H251: 250 | J251: 30 | K251: 10 | L251: 200 | O251: 15
A252: 950 | E252: 60 | G252: 500 | H252: 110 | J252: 100 | K252: 30 | L252: 3 | O252: 100
A253: 980 | E253: 250 | G253: 200 | H253: 200 | J253: 200 | K253: 30 | L253: 30 | O253: 40
... A279: 680 | E279: 200 | G279: 100 | H279: 200 | J279: 50 | K279: 20 | L279: 200 | O279: 50
A280: 830 | G280: 50 | H280: 75 | J280: 20 | K280: 15 | L280: 50 | O280: 10
A281: 800 | G281: 75 | H281: 200 | J281: 50 | K281: 10 | L281: 30 | O281: 7.99
A282: 1200 | G282: 100 | H282: 100 | J282: 40 | K282: 10 | L282: 100 | O282: 100
A283: 710 | G283: 400 | H283: 200 | J283: 20 | K283: 90 | L283: 200 | O283: 50
...

Sheet Monthly Expenses
A1: In this worksheet, you will compare the expenses of the class (according to your ID assignment), with your personal expenses
B3: Class expenses | C3: =SUM(B8:B24) -> 4664.2849
B4: My expenses | C4: =SUM(C8:C24) -> 1775
B5: Difference | C5: =C3-C4 -> 2889.2849
A7: Gainesville: Monthly Expenses | B7: Class expenses | C7: My Expenses | E7: My monthly expenses ordered from Largest to smallest
A8: Home (Rent rent insurance etc) | B8: =AVERAGE('Class Budget Data'!A:A) -> 1022.6546 | C8: 850 | E8: Item | F8: My expenses | H8: Item | I8: My expenses
A9: Cell phone | B9: =AVERAGE('Class Budget Data'!B:B) -> 67.928856 | C9: 10 | E9: Cable or Internet | F9: 0 | H9: Car | I9: 0 | K9: Using the VLookUp function
A10: Cable or Internet | B10: =AVERAGE('Class Budget Data'!C:C) -> 55.688616 | C10: 0 | E10: Car - Monthly payment | F10: 0 | H10: Clothing | I10: 50 | K10: Type below an expense item to find the value
A11: Car - Monthly payment | B11: =AVERAGE('Class Budget Data'!D:D) -> 514.917 | C11: 0 | E11: Other Transportation (bus etc) | F11: 0 | H11: Fun | I11: 100 | K11: Travel | L11: =VLOOKUP(K11,H9:I25,2,FALSE) -> 300
A12: Car - Gasoline | B12: =AVERAGE('Class Budget Data'!E:E) -> 101.03331 | C12: 100 | E12: Daycare/kids | F12: 0 | H12: Gas | I12: 100
A13: Other Transportation (bus etc) | B13: =AVERAGE('Class Budget Data'!F:F) -> 68.022727 | C13: 0 | E13: School supplies | F13: 0 | H13: Groceries | I13: 100
A14: Groceries (e.g. Walmart) | B14: =AVERAGE('Class Budget Data'!G:G) -> 209.8019 | C14: 100 | E14: Savings for unexpected expenses | F14: 0 | H14: Home | I14: 850
A15: Restaurants / fast food/ coffee shops | B15: =AVERAGE('Class Budget Data'!H:H) -> 180.14286 | C15: 250 | E15: Savings for Retirement (e.g savings to ROTH IRA account) | F15: 0 | H15: Internet | I15: 0
A16: Daycare/kids | B16: =AVERAGE('Class Budget Data'!I:I) -> 500 | C16: 0 | E16: Payments to loans | F16: 0 | H16: Kids | I16: 0
A17: Clothing | B17: =AVERAGE('Class Budget Data'!J:J) -> 91.130699 | C17: 50 | E17: Cell phone | F17: 10 | H17: Loans | I17: 0
A18: School supplies | B18: =AVERAGE('Class Budget Data'!K:K) -> 34.674831 | C18: 0 | E18: Subscriptions (Apple music Amazon music Netflix Disney + etc) | F18: 15 | H18: Other | I18: 0
A19: Fun stuff (parties movies hobbies etc) | B19: =AVERAGE('Class Budget Data'!L:L) -> 137.37143 | C19: 100 | E19: Clothing | F19: 50 | H19: Phone | I19: 10
A20: Savings for unexpected expenses | B20: =AVERAGE('Class Budget Data'!M:M) -> 367.22917 | C20: 0 | E20: Car - Gasoline | F20: 100 | H20: Restaurants | I20: 250
A21: Savings for Retirement (e.g savings to ROTH IRA account) | B21: =AVERAGE('Class Budget Data'!N:N) -> 800.83171 | C21: 0 | E21: Groceries (e.g. Walmart) | F21: 100 | H21: Retirement | I21: 0
A22: Subscriptions (Apple music Amazon music Netflix Disney + etc) | B22: =AVERAGE('Class Budget Data'!O:O) -> 52.663438 | C22: 15 | E22: Fun stuff (parties movies hobbies etc) | F22: 100 | H22: Emergency | I22: 0
A23: Travel | B23: =AVERAGE('Class Budget Data'!P:P) -> 162.44385 | C23: 300 | E23: Restaurants / fast food/ coffee shops | F23: 250 | H23: School | I23: 0
A24: Payments to loans | B24: =AVERAGE('Class Budget Data'!Q:Q) -> 297.75 | C24: 0 | E24: Travel | F24: 300 | H24: Subscriptions | I24: 15
E25: Home (Rent rent insurance etc) | F25: 850 | H25: Travel | I25: 300

Sheet Charts
A1: 3D - Column chart comparison of class expenses vs my expenses | I1: Pie chart of monthly expenses
